README.md
setup.py
graphene_prisma/__init__.py
graphene_prisma/__version__.py
graphene_prisma/playground.py
graphene_prisma.egg-info/PKG-INFO
graphene_prisma.egg-info/SOURCES.txt
graphene_prisma.egg-info/dependency_links.txt
graphene_prisma.egg-info/requires.txt
graphene_prisma.egg-info/top_level.txt
graphene_prisma/responder/__init__.py
graphene_prisma/responder/graphql.py
graphene_prisma/starlette/__init__.py
graphene_prisma/starlette/graphql.py
tests/__init__.py
tests/test_test.py