Metadata-Version: 2.1
Name: graphene-prisma
Version: 0.1.0
Summary: Brings prisma playground to Graphene and more
Home-page: https://github.com/taoufik07/graphene-prisma
Author: Taoufik Abbassid
Author-email: abacidtaoufik@gmail.com
License: BSD
Platform: UNKNOWN
Classifier: Environment :: Web Environment
Classifier: Intended Audience :: Developers
Classifier: License :: OSI Approved :: BSD License
Classifier: Operating System :: OS Independent
Classifier: Programming Language :: Python :: 3
Classifier: Programming Language :: Python :: 3.6
Classifier: Programming Language :: Python :: 3.7
Requires-Python: >=3.6
Provides-Extra: responder
Provides-Extra: starlette
